resque_exporter/__init__.py
resque_exporter/__main__.py
resque_exporter/collector.py
resque_exporter-0.0.1.dist-info/LICENSE.md
resque_exporter-0.0.1.dist-info/METADATA
resque_exporter-0.0.1.dist-info/WHEEL
resque_exporter-0.0.1.dist-info/entry_points.txt
resque_exporter-0.0.1.dist-info/top_level.txt
resque_exporter-0.0.1.dist-info/RECORD
